misID_data/__init__.py
misID_data/model/v2/ETOS/2011/bpkkk.csv
misID_data/model/v2/ETOS/2011/bpkpipi.csv
misID_data/model/v2/ETOS/2011/pars_misID.json
misID_data/model/v2/ETOS/2012/bpkkk.csv
misID_data/model/v2/ETOS/2012/bpkpipi.csv
misID_data/model/v2/ETOS/2012/pars_misID.json
misID_data/model/v2/ETOS/2015/bpkkk.csv
misID_data/model/v2/ETOS/2015/bpkpipi.csv
misID_data/model/v2/ETOS/2015/pars_misID.json
misID_data/model/v2/ETOS/2016/bpkkk.csv
misID_data/model/v2/ETOS/2016/bpkpipi.csv
misID_data/model/v2/ETOS/2016/pars_misID.json
misID_data/model/v2/ETOS/2017/bpkkk.csv
misID_data/model/v2/ETOS/2017/bpkpipi.csv
misID_data/model/v2/ETOS/2017/pars_misID.json
misID_data/model/v2/ETOS/2018/bpkkk.csv
misID_data/model/v2/ETOS/2018/bpkpipi.csv
misID_data/model/v2/ETOS/2018/pars_misID.json
misID_data/model/v2/GTIS/2011/bpkkk.csv
misID_data/model/v2/GTIS/2011/bpkpipi.csv
misID_data/model/v2/GTIS/2011/pars_misID.json
misID_data/model/v2/GTIS/2012/bpkkk.csv
misID_data/model/v2/GTIS/2012/bpkpipi.csv
misID_data/model/v2/GTIS/2012/pars_misID.json
misID_data/model/v2/GTIS/2015/bpkkk.csv
misID_data/model/v2/GTIS/2015/bpkpipi.csv
misID_data/model/v2/GTIS/2015/pars_misID.json
misID_data/model/v2/GTIS/2016/bpkkk.csv
misID_data/model/v2/GTIS/2016/bpkpipi.csv
misID_data/model/v2/GTIS/2016/pars_misID.json
misID_data/model/v2/GTIS/2017/bpkkk.csv
misID_data/model/v2/GTIS/2017/bpkpipi.csv
misID_data/model/v2/GTIS/2017/pars_misID.json
misID_data/model/v2/GTIS/2018/bpkkk.csv
misID_data/model/v2/GTIS/2018/bpkpipi.csv
misID_data/model/v2/GTIS/2018/pars_misID.json
misID_data/model/v2-tgtcbdt/ETOS/2011/bpkkk.csv
misID_data/model/v2-tgtcbdt/ETOS/2011/bpkpipi.csv
misID_data/model/v2-tgtcbdt/ETOS/2011/pars_misID.json
misID_data/model/v2-tgtcbdt/ETOS/2012/bpkkk.csv
misID_data/model/v2-tgtcbdt/ETOS/2012/bpkpipi.csv
misID_data/model/v2-tgtcbdt/ETOS/2012/pars_misID.json
misID_data/model/v2-tgtcbdt/ETOS/2015/bpkkk.csv
misID_data/model/v2-tgtcbdt/ETOS/2015/bpkpipi.csv
rk_hadmisid_study-0.1.9.dist-info/METADATA
rk_hadmisid_study-0.1.9.dist-info/WHEEL
rk_hadmisid_study-0.1.9.dist-info/top_level.txt
rk_hadmisid_study-0.1.9.dist-info/RECORD
