Metadata-Version: 2.1
Name: rk_hadmisid_study
Version: 0.1.9
Summary: All tools and scripts used in the study of the hadron mis-ID.
Author: xuzh
Requires-Dist: rx-differential-crosscheck-fits >=0.0.3
Requires-Dist: rx-scripts >=0.2.8
Requires-Dist: rx-tools >=0.2.0
